{"details":[{"dua_global_id":"153","dua_segment_id":"","top":"","arabic_diacless":"اللٰهم أعذه من عذاب القبر","arabic":"اَللّٰهُمَّ أَعِذْهُ مِنْ عَذَابِ الْقَبْرِ","transliteration":"আল্লা-হুম্মা আ‘য়িযহু মিন আযা-বিল ক্বাবরি","translations":"হে আল্লাহ! এ শিশুকে কবরের আযাব থেকে রক্ষা করুন।","bottom":"","reference":"সা‘ঈদ ইবনুল মুসাইয়্যেব বলেন, আমি আবু হুরাইরা রাদিয়াল্লাহু আনহুর পিছনে একটি শিশুর জানাযার সালাত আদায় করেছি, যে শিশু কখনও কোনো গুনাহ করে নি, তখন আমি তাকে (উপরোক্ত দো‘আটি) বলতে শুনলাম....। হাদীসটি ইমাম মালেক তার মুওয়াত্তা গ্রন্থে সংকলন করেন, ১/২৮৮; ইবন আবী শাইবাহ তার মুসান্নাফ গ্রন্থে, ৩/২১৭; বাইহাকী, ৪/৯। আর শাইখ শু‘আইব আল-আরনাউত শারহুস সুন্নাহ লিল বাগভীর তাহকীকে ৫/৩৫৭, এটার সনদকে সহীহ বলেছেন।"}],"pageTitle":"নাবালক শিশুদের জন্য জানাযার সালাতে দো‘আ #১"}