{"details":[{"dua_global_id":"229","dua_segment_id":"1","top":"","arabic_diacless":"سبحان اللٰه","arabic":"سُبْحَانَ اللّٰهِ","transliteration":"সুবহা-নাল্লা-হ","translations":"আল্লাহ পবিত্র-মহান। [১]","bottom":"","reference":""},{"dua_global_id":"229","dua_segment_id":"2","top":"","arabic_diacless":"اللٰه أكبر","arabic":"اَللّٰهُ أَكْبَرُ","transliteration":"আল্লা-হু আকবার","translations":"আল্লাহ সবচেয়ে বড়। [২]","bottom":"","reference":"[১] বুখারী, (ফাতহুল বারীসহ) ১/২১০, ৩৯০, ৪১৪, নং ১১৫, ৩৫৯৯, ৬২১৮; মুসলিম ৪/১৮৫৭, নং ১৬৭৪ \r\n[২] বুখারী, (ফাতহুল বারীসহ) ৮/৪৪১, নং ৪৭৪১; তিরমিযী নং ২১৮০; আন- নাসাঈ ফিল কুবরা, নং ১১১৮৫। আরও দেখুন, সহীহুত তিরমিযী ২/১০৩, ২/২৩৫, আহমাদ-৫/২১৮, নং ২১৯০০।"}],"pageTitle":"আশ্চর্যজনক ও আনন্দজনক বিষয়ের পর দো‘আ"}