{"details":[{"dua_global_id":"349","dua_segment_id":"","top":"বিভিন্ন সাহাবী থেকে তাশাহহুদ বর্ণিত। ইবনু মাস’ঊদ (রা) বলেন, আমরা রাসূলুল্লাহ -এর পিছে সালাত আদায়ের সময় বসলে বলতাম: আল্লাহর উপর সালাম, ফিরিশতাগণের উপর সালাম, অমুকের উপর সালাম, ...। রাসূলুল্লাহ  একদিন আমাদেরকে বললেন : আল্লাহই সালাম (কাজেই, তাঁকে সালাম প্রদান করা ঠিক নয়)। অতএব, তোমরা যখন সালাতের মধ্যে বসবে তখন বলবে :","arabic_diacless":"التحيات للٰه والصلوات والطيبات، السلام عليك أيها النبي ورحمة اللٰه وبركاته، السلام علينا وعلی عباد اللٰه الصالحين (فإذا قالها أصابت كل عبد للٰه صالح في السماء والأرض) أشهد أن لا إلٰه إلا اللٰه وأشهد أن محمدا عبده ورسوله (ثم يتخير من المسألة ما شاء)","arabic":"التَّحِيَّاتُ ِلِلّٰهِ وَالصَّلَوَاتُ وَالطَّيِّبَاتُ، اَلسَّلَامُ عَلَيْكَ أَيُّهَا النَّبِيُّ وَرَحْمَةُ اللّٰهِ وَبَرَكَاتُهُ، اَلسَّلَامُ عَلَيْنَا وَعَلَی عِبَادِ اللّٰهِ الصَّالِحِيْنَ (فَإِذَا قَالَهَا أَصَابَتْ كُلَّ عَبْدٍ لِلّٰهِ صَالِحٍ فِي السَّمَاءِ وَالأَرْضِ) أَشْهَدُ أَنْ لَا إِلٰهَ إِلَّا اللّٰهُ وَأَشْهَدُ أَنَّ مُحَمَّدًا عَبْدُهُ وَرَسُوْلُهُ (ثُمَّ يَتَخَيَّرُ مِنَ الْمَسْأَلَةِ مَا شَاءَ)","transliteration":"","translations":"মর্যাদাজ্ঞাপন-অভিবাদন আল্লাহর জন্য এবং ইবাদত-প্রার্থনা এবং পবিত্র কর্ম ও দানসমূহ (সবই আল্লাহর জন্য)। সালাম আপনার উপর, হে নবী; এবং আল্লাহর রহমত ও তাঁর বরকতসমূহ। সালাম আমাদের উপর এবং আল্লাহর নেককার বান্দার উপর। (রাসূলুল্লাহ  বলেন: এ কথা বললে আসমান ও যমিনে আল্লাহর সকল নেক বান্দাকেই সালাম দেওয়া হয়ে যাবে) আমি সাক্ষ্য প্রদান করছি যে, আল্লাহ ছাড়া কোনো উপাস্য নেই। এবং সাক্ষ্য দিচ্ছি যে, মুহাম্মাদ তাঁর বান্দা (দাস) ও রাসূল (প্রেরিত বার্তাবাহক)। (রাসূলুল্লাহ  বলেন: এরপর মুসল্লী নিজের জন্য পছন্দমতো প্রার্থনা বা দু‘আ করবে।)","bottom":"","reference":"[১]বুখারী(১৬-সিফাতিস সালাত,৬৪-৬৬ তাশাহহুদ ফিল আখিরা...) ১/২৮৬-২৮৭ (ভা ১/১১০); মুসলিম(৪-সালাত, ১৬-বাবুত তাশাহহুদ) ১/৩০১ (ভা ১/১৭৩); ইবন হাজার,ফাতহুল বারী ২/৩১৮-৩২২"}],"pageTitle":"যিকর নং ৬৫: তাশাহহুদ (আত-তাহিয়্যাত)"}