{"details":[{"dua_global_id":"387","dua_segment_id":"","top":"","arabic_diacless":"باسمك ربي وضعت جنبي فاغفر لي ذنبي","arabic":"بِاسْمِكَ رَبِّيْ وَضَعْتُ جَنْبِيْ فَاغْفِرْ لِيْ ذَنْبِيْ","transliteration":"বিসমিকা রাব্বী, ওয়াদ্বা‘অ্তু জানবী, ফাগফির লী যাম্বী।","translations":"হে আমার প্রভু , আপনারই নামে শয়ন করলাম। আপনি আমার গোনাহ ক্ষমা করে দিন।","bottom":"আব্দুল্লাহ ইবনু আমর (রা) বলেন, নবীজী (স) যখন বিছানায় ঘুমের জন্য শয়ন করতেন, তখন উপরোল্লেখিত দু‘আটি বলতেন। হাদীসটি হাসান।","reference":"মুুসনাদ আহমদ ২/১৭৩; হাইসামী,মাজমাউয যাওয়াইদ ১০/১২৩"}],"pageTitle":"যিকর নং ১৬০:"}