{"details":[{"dua_global_id":"234","dua_segment_id":"","top":"","arabic_diacless":"بسم اللٰه واللٰه أكبر [اللٰهم منك ولك] اللٰهم تقبل مني","arabic":"بِسْمِ اللّٰهِ وَاللّٰهُ أَكْبَرُ [اَللّٰهُمَّ مِنْكَ وَلَكَ] اَللّٰهُمَّ تَقَبَّلْ مِنِّيْ","transliteration":"Bismillaahi wallaahu 'Akbar [Allaahumma minka wa laka] Allaahumma taqabbal minnee.","translations":"With the Name of Allah, Allah is the Most Great! [O Allah, from You and to You.] O Allah, accept it from me.","bottom":"","reference":"At-Tirmithi 5/82, Ahmad 4/400, Abu Dawud 4/ 308. See also Al-Albani, Sahih At-Tirmithi 2/354."}],"pageTitle":"When slaughtering or sacrificing an animal"}